gemviz/LICENSE
gemviz/README.md
gemviz/__init__.py
gemviz/aboutdialog.py
gemviz/app.py
gemviz/bluesky_runs_catalog.py
gemviz/bluesky_runs_catalog_run_viz.py
gemviz/bluesky_runs_catalog_search.py
gemviz/bluesky_runs_catalog_table_model.py
gemviz/bluesky_runs_catalog_table_view.py
gemviz/chartview.py
gemviz/curve_manager.py
gemviz/date_time_range_slider.py
gemviz/fit_manager.py
gemviz/fit_models.py
gemviz/licensedialog.py
gemviz/mainwindow.py
gemviz/range_slider.py
gemviz/select_fields_tablemodel.py
gemviz/select_fields_tableview.py
gemviz/select_stream_fields.py
gemviz/tapi.py
gemviz/tiledserverdialog.py
gemviz/user_settings.py
gemviz/utils.py
gemviz/resources/aboutdialog.ui
gemviz/resources/apply.png
gemviz/resources/back.png
gemviz/resources/bluesky_runs_catalog.ui
gemviz/resources/bluesky_runs_catalog_run_viz.ui
gemviz/resources/bluesky_runs_catalog_search.ui
gemviz/resources/bluesky_runs_catalog_table_view.ui
gemviz/resources/date_time_range_slider.ui
gemviz/resources/delete.png
gemviz/resources/first.png
gemviz/resources/last.png
gemviz/resources/licensedialog.ui
gemviz/resources/mainwindow.ui
gemviz/resources/next.png
gemviz/resources/open.png
gemviz/resources/plus.png
gemviz/resources/refresh.png
gemviz/resources/select_fields_tableview.ui
gemviz/resources/select_stream_fields.ui
gemviz/resources/set.png
gemviz/resources/tiledserverdialog.ui
gemviz/tests/__init__.py
gemviz/tests/test_aboutdialog.py
gemviz/tests/test_app.py
gemviz/tests/test_chartview.py
gemviz/tests/test_init.py
gemviz/tests/test_utils.py
gemviz-1.0.0.dist-info/METADATA
gemviz-1.0.0.dist-info/WHEEL
gemviz-1.0.0.dist-info/entry_points.txt
gemviz-1.0.0.dist-info/top_level.txt
gemviz-1.0.0.dist-info/RECORD
