Metadata-Version: 2.4
Name: gemviz
Version: 1.0.0
Summary: Visualize Bluesky data from tiled server.
Author: Ollivier Gassant
Author-email: Fanny Rodolakis <rodolakis@anl.gov>, Pete Jemian <prjemian@gmail.com>
Maintainer-email: Fanny Rodolakis <rodolakis@anl.gov>, Pete Jemian <prjemian@gmail.com>
License: Copyright (c) 2023-2025, UChicago Argonne, LLC
Project-URL: Homepage, https://github.com/BCDA-APS/gemviz
Project-URL: Bug Tracker, https://github.com/BCDA-APS/gemviz/issues
Keywords: bluesky,databroker,tiled,catalog
Classifier: Development Status :: 3 - Alpha
Classifier: Environment :: Console
Classifier: Intended Audience :: Science/Research
Classifier: License :: Freely Distributable
Classifier: License :: Public Domain
Classifier: Operating System :: OS Independent
Classifier: Programming Language :: Python :: 3
Classifier: Programming Language :: Python
Classifier: Topic :: Scientific/Engineering :: Astronomy
Classifier: Topic :: Scientific/Engineering :: Bio-Informatics
Classifier: Topic :: Scientific/Engineering :: Chemistry
Classifier: Topic :: Scientific/Engineering :: Mathematics
Classifier: Topic :: Scientific/Engineering :: Physics
Classifier: Topic :: Scientific/Engineering :: Visualization
Classifier: Topic :: Scientific/Engineering
Classifier: Topic :: Utilities
Requires-Python: >=3.9
Requires-Dist: matplotlib
Requires-Dist: pyRestTable
Requires-Dist: tiled
Requires-Dist: scipy
Requires-Dist: bluesky-tiled-plugins
Provides-Extra: dev
Requires-Dist: black; extra == "dev"
Requires-Dist: flake8; extra == "dev"
Requires-Dist: isort; extra == "dev"
Requires-Dist: pydata-sphinx-theme; extra == "dev"
Requires-Dist: pytest; extra == "dev"
Requires-Dist: pytest-cov; extra == "dev"
Requires-Dist: pytest-qt; extra == "dev"
Requires-Dist: sphinx; extra == "dev"
Requires-Dist: sphinx-tabs; extra == "dev"
Provides-Extra: doc
Requires-Dist: coverage; extra == "doc"
Requires-Dist: coveralls; extra == "doc"
Requires-Dist: pydata-sphinx-theme; extra == "doc"
Requires-Dist: pytz; extra == "doc"
Requires-Dist: setuptools-scm; extra == "doc"
Requires-Dist: sphinx; extra == "doc"
Requires-Dist: sphinx-design; extra == "doc"
Requires-Dist: sphinx-tabs; extra == "doc"
Requires-Dist: tzdata; extra == "doc"
Provides-Extra: all
Requires-Dist: gemviz[dev,doc]; extra == "all"
